material_design_icons_pack-7.4.47.dist-info/METADATA
material_design_icons_pack-7.4.47.dist-info/WHEEL
material_design_icons_pack-7.4.47.dist-info/licenses/LICENSE
material_design_icons_pack/__init__.py
material_design_icons_pack/__init__.pyi
material_design_icons_pack/material_design_icons_pack.abi3.so
material_design_icons_pack/py.typed
material_design_icons_pack-7.4.47.dist-info/RECORD
