Metadata-Version: 2.4
Name: material-design-icons-pack
Version: 7.4.47
Classifier: Programming Language :: Rust
Classifier: Programming Language :: Python :: Implementation :: CPython
Classifier: Programming Language :: Python :: Implementation :: PyPy
License-File: LICENSE
Summary: A redistribution of @mdi/svg npm package's SVG and metadata.
License: Apache-2.0
Requires-Python: >=3.8
Project-URL: source, https://github.com/2bndy5/redist-icons
